README
setup.py
src/cloud_dns_cli/__init__.py
src/cloud_dns_cli/cloud_dns_cli.py
src/cloud_dns_cli.egg-info/PKG-INFO
src/cloud_dns_cli.egg-info/SOURCES.txt
src/cloud_dns_cli.egg-info/dependency_links.txt
src/cloud_dns_cli.egg-info/entry_points.txt
src/cloud_dns_cli.egg-info/requires.txt
src/cloud_dns_cli.egg-info/top_level.txt