Metadata-Version: 1.1
Name: cloud-dns-cli
Version: 0.9.04
Summary: A CLI Tool for interacting with RackSpace Cloud DNS
Home-page: https://github.com/ephur/cloud_dns
Author: Richard Maynard
Author-email: richard.maynard@gmail.com
License: Apache 2.0
Keywords: rackspace cloud dns cli pyrax
Platform: UNKNOWN
Classifier: Development Status :: 4 - Beta
Classifier: Environment :: Console
Classifier: Intended Audience :: Developers
Classifier: Intended Audience :: System Administrators
Classifier: Intended Audience :: Information Technology
Classifier: License :: OSI Approved :: Apache Software License
Classifier: Natural Language :: English
Classifier: Operating System :: OS Independent
Classifier: Programming Language :: Python
Classifier: Topic :: System :: Systems Administration
